git_os_job/__init__.py
git_os_job/cmd.py
git_os_job-1.1.3.dist-info/AUTHORS
git_os_job-1.1.3.dist-info/LICENSE
git_os_job-1.1.3.dist-info/METADATA
git_os_job-1.1.3.dist-info/WHEEL
git_os_job-1.1.3.dist-info/entry_points.txt
git_os_job-1.1.3.dist-info/pbr.json
git_os_job-1.1.3.dist-info/top_level.txt
git_os_job-1.1.3.dist-info/RECORD
