Metadata-Version: 2.1
Name: git-os-job
Version: 1.1.3
Summary: Show the OpenStack job logs for a commit
Home-page: https://github.com/dhellmann/git-os-job
Author: Doug Hellmann
Author-email: doug@doughellmann.com
License: Apache License (2.0)
Keywords: git gerrit review
Platform: UNKNOWN
Classifier: Programming Language :: Python :: 2
Classifier: Programming Language :: Python :: 3
Classifier: Programming Language :: Python
Classifier: Development Status :: 5 - Production/Stable
Classifier: Environment :: Console
Classifier: Environment :: OpenStack
Classifier: Intended Audience :: Developers
Classifier: Intended Audience :: Information Technology
Classifier: License :: OSI Approved :: Apache Software License
Classifier: Operating System :: OS Independent
